EXPT6/graycode.v
module srff(input S, input R, input clk, input rst, output reg Q, output Qbar);

always @(posedge clk)
if (!rst)
    Q <= 0;
else begin
    if(!S & !R)
        Q <= Q;
    else if(!S & R)
        Q <= 0;
    else if(S & !R)
        Q <= 1;
end
assign Qbar = !Q;
endmodule

module graycode(input rst, input clk, output [3:0] out);

wire r0,r1,r2,r3,s0,s1,s2,s3,s4,q0,q1,q2,q3,qn0,qn1,qn2,qn3;

assign s0 = (!q3 & !q2 & !q1) | (!q3 & q2 & q1) | (q3 & !q2 & q1) | (q3 & q2 & !q1);
assign r0 = (!q3 & !q2 & q1) | (!q3 & q2 & !q1) | (q3 & !q2 & !q1) | (q3 & q2 & q1);

assign s1 = (!q3 & !q2 & q0) | (q3 & q2 & q0);
assign r1 = (!q3 & q2 & q0) | (q3 & !q2 & q0);

assign s2 = (!q3 & q1 & !q0);
assign r2 = (q3 & q1 & !q0);

assign s3 = (q2 & !q1 & !q0);
assign r3 = (!q2 & !q1 & !q0);

srff sr3 (s3, r3, clk, rst, q3, qn3);
srff sr2 (s2, r2, clk, rst, q2, qn2);
srff sr1 (s1, r1, clk, rst, q1, qn1);
srff sr0 (s0, r0, clk, rst, q0, qn0);

assign out = {q3, q2, q1, q0};

endmodule

EXPT6/tb_graycode.v
module tb_graycode;  
    reg clk;
    reg rstn;  
    wire [3:0] out;  
    graycode counter (rstn, clk, out);  
    always #5 clk = ~clk;  
    initial begin
      $dumpfile("graycode.vcd");
			$dumpvars(0, tb_graycode);
      $monitor($time," %b", out);
      rstn <= 0;  
      clk <= 0;  
      repeat (1) @ (posedge clk);  
      rstn <= 1;  
      repeat (17) @ (posedge clk);  
      $finish;  
   end  
endmodule

EXPT6/graycode.vcd
$date
	Mon May 17 23:05:12 2021
$end
$version
	Icarus Verilog
$end
$timescale
	1s
$end
$scope module tb_graycode $end
$var wire 4 ! out [3:0] $end
$var reg 1 " clk $end
$var reg 1 # rstn $end
$scope module counter $end
$var wire 1 " clk $end
$var wire 1 $ r0 $end
$var wire 1 % r1 $end
$var wire 1 & r2 $end
$var wire 1 ' r3 $end
$var wire 1 # rst $end
$var wire 1 ( s0 $end
$var wire 1 ) s1 $end
$var wire 1 * s2 $end
$var wire 1 + s3 $end
$var wire 1 , qn3 $end
$var wire 1 - qn2 $end
$var wire 1 . qn1 $end
$var wire 1 / qn0 $end
$var wire 1 0 q3 $end
$var wire 1 1 q2 $end
$var wire 1 2 q1 $end
$var wire 1 3 q0 $end
$var wire 4 4 out [3:0] $end
$scope module sr0 $end
$var wire 1 $ R $end
$var wire 1 ( S $end
$var wire 1 " clk $end
$var wire 1 # rst $end
$var wire 1 / Qbar $end
$var reg 1 3 Q $end
$upscope $end
$scope module sr1 $end
$var wire 1 % R $end
$var wire 1 ) S $end
$var wire 1 " clk $end
$var wire 1 # rst $end
$var wire 1 . Qbar $end
$var reg 1 2 Q $end
$upscope $end
$scope module sr2 $end
$var wire 1 & R $end
$var wire 1 * S $end
$var wire 1 " clk $end
$var wire 1 # rst $end
$var wire 1 - Qbar $end
$var reg 1 1 Q $end
$upscope $end
$scope module sr3 $end
$var wire 1 ' R $end
$var wire 1 + S $end
$var wire 1 " clk $end
$var wire 1 # rst $end
$var wire 1 , Qbar $end
$var reg 1 0 Q $end
$upscope $end
$upscope $end
$upscope $end
$enddefinitions $end
#0
$dumpvars
bx 4
x3
x2
x1
x0
x/
x.
x-
x,
x+
x*
x)
x(
x'
x&
x%
x$
0#
0"
bx !
$end
#5
1(
0$
1'
0+
0&
0*
0%
0)
1,
00
1-
01
1.
02
1/
b0 !
b0 4
03
1#
1"
#10
0"
#15
1)
0'
0/
b1 !
b1 4
13
1"
#20
0"
#25
0(
1$
0.
b11 !
b11 4
12
1"
#30
0"
#35
0)
1*
1/
b10 !
b10 4
03
1"
#40
0"
#45
0$
1(
0-
b110 !
b110 4
11
1"
#50
0"
#55
1%
0*
0/
b111 !
b111 4
13
1"
#60
0"
#65
1$
0(
1.
b101 !
b101 4
02
1"
#70
0"
#75
0%
1+
1/
b100 !
b100 4
03
1"
#80
0"
#85
0$
1(
0,
b1100 !
b1100 4
10
1"
#90
0"
#95
1)
0+
0/
b1101 !
b1101 4
13
1"
#100
0"
#105
0(
1$
0.
b1111 !
b1111 4
12
1"
#110
0"
#115
0)
1&
1/
b1110 !
b1110 4
03
1"
#120
0"
#125
1(
0$
1-
b1010 !
b1010 4
01
1"
#130
0"
#135
1%
0&
0/
b1011 !
b1011 4
13
1"
#140
0"
#145
1$
0(
1.
b1001 !
b1001 4
02
1"
#150
0"
#155
0%
1'
1/
b1000 !
b1000 4
03
1"
#160
0"
#165
1(
0$
1,
b0 !
b0 4
00
1"
#170
0"
#175
1)
0'
0/
b1 !
b1 4
13
1"
