EXPT6/ringcounter.v
module dff(input D, input iniv, input clk, input rst, output reg Q, output Qbar);
always @(posedge clk)
if(!rst) 
    Q <= iniv;
else
    Q <= D;
assign Qbar = !Q;
endmodule

module ringcounter(input rst, input clk, output [3:0] out);

wire d0,d1,d2,d3,q0,q1,q2,q3,qn0,qn1,qn2,qn3;

assign d0 = q1;
assign d1 = q2;
assign d2 = q3;
assign d3 = q1^q0;

dff df0 (d0, 1'b1, clk, rst, q0, qn0);
dff df1 (d1, 1'b0, clk, rst, q1, qn1);
dff df2 (d2, 1'b0, clk, rst, q2, qn2);
dff df3 (d3, 1'b0, clk, rst, q3, qn3);

assign out = {d3,d2,d1,d0};
endmodule

EXPT6/tb_ringcounter.v
module tb_ringcounter;  
    reg clk;
    reg rstn;  
    wire [3:0] out;  
    ringcounter counter (rstn, clk, out);  
    always #5 clk = ~clk;  
    initial begin
      $dumpfile("ringcounter.vcd");
			$dumpvars(0, tb_ringcounter);
      $monitor($time," %b", out);
      rstn <= 0;  
      clk <= 0;  
      repeat (1) @ (posedge clk);  
      rstn <= 1;  
      repeat (17) @ (posedge clk);  
      $finish;  
   end  
endmodule

EXPT6/ringcounter.vcd
$date
	Wed May 19 01:23:59 2021
$end
$version
	Icarus Verilog
$end
$timescale
	1s
$end
$scope module tb_ringcounter $end
$var wire 4 ! out [3:0] $end
$var reg 1 " clk $end
$var reg 1 # rstn $end
$scope module counter $end
$var wire 1 " clk $end
$var wire 1 $ d0 $end
$var wire 1 % d1 $end
$var wire 1 & d2 $end
$var wire 1 ' d3 $end
$var wire 1 # rst $end
$var wire 1 ( qn3 $end
$var wire 1 ) qn2 $end
$var wire 1 * qn1 $end
$var wire 1 + qn0 $end
$var wire 1 , q3 $end
$var wire 1 - q2 $end
$var wire 1 . q1 $end
$var wire 1 / q0 $end
$var wire 4 0 out [3:0] $end
$scope module df0 $end
$var wire 1 $ D $end
$var wire 1 " clk $end
$var wire 1 1 iniv $end
$var wire 1 # rst $end
$var wire 1 + Qbar $end
$var reg 1 / Q $end
$upscope $end
$scope module df1 $end
$var wire 1 % D $end
$var wire 1 " clk $end
$var wire 1 2 iniv $end
$var wire 1 # rst $end
$var wire 1 * Qbar $end
$var reg 1 . Q $end
$upscope $end
$scope module df2 $end
$var wire 1 & D $end
$var wire 1 " clk $end
$var wire 1 3 iniv $end
$var wire 1 # rst $end
$var wire 1 ) Qbar $end
$var reg 1 - Q $end
$upscope $end
$scope module df3 $end
$var wire 1 ' D $end
$var wire 1 " clk $end
$var wire 1 4 iniv $end
$var wire 1 # rst $end
$var wire 1 ( Qbar $end
$var reg 1 , Q $end
$upscope $end
$upscope $end
$upscope $end
$enddefinitions $end
#0
$dumpvars
04
03
02
11
bx 0
x/
x.
x-
x,
x+
x*
x)
x(
x'
x&
x%
x$
0#
0"
bx !
$end
#5
1'
0+
1/
1*
0$
0.
1)
0%
0-
1(
b1000 !
b1000 0
0&
0,
1#
1"
#10
0"
#15
0'
0(
b100 !
b100 0
1&
1,
1+
0/
1"
#20
0"
#25
0)
1%
1-
1(
b10 !
b10 0
0&
0,
1"
#30
0"
#35
1'
1)
0%
0-
0*
b1001 !
b1001 0
1$
1.
1"
#40
0"
#45
0+
1/
1*
0$
0.
0(
b1100 !
b1100 0
1&
1,
1"
#50
0"
#55
0'
0)
b110 !
b110 0
1%
1-
1+
0/
1"
#60
0"
#65
1'
0*
1$
1.
1(
b1011 !
b1011 0
0&
0,
1"
#70
0"
#75
0'
0(
1&
1,
1)
b101 !
b101 0
0%
0-
0+
1/
1"
#80
0"
#85
1'
1*
0$
0.
0)
1%
1-
1(
b1010 !
b1010 0
0&
0,
1"
#90
0"
#95
0(
1&
1,
1)
0%
0-
0*
b1101 !
b1101 0
1$
1.
1+
0/
1"
#100
0"
#105
0+
1/
1*
0$
0.
0)
b1110 !
b1110 0
1%
1-
1"
#110
0"
#115
0*
b1111 !
b1111 0
1$
1.
1+
0/
1"
#120
0"
#125
b111 !
b111 0
0'
0+
1/
1"
#130
0"
#135
1(
b11 !
b11 0
0&
0,
1"
#140
0"
#145
1)
b1 !
b1 0
0%
0-
1"
#150
0"
#155
1'
1*
b1000 !
b1000 0
0$
0.
1"
#160
0"
#165
0'
1+
0/
0(
b100 !
b100 0
1&
1,
1"
#170
0"
#175
1(
0&
0,
0)
b10 !
b10 0
1%
1-
1"
